plover_keyboard_plus/__init__.py
plover_keyboard_plus/machine.py
plover_keyboard_plus-0.0.5.dist-info/LICENSE
plover_keyboard_plus-0.0.5.dist-info/METADATA
plover_keyboard_plus-0.0.5.dist-info/WHEEL
plover_keyboard_plus-0.0.5.dist-info/entry_points.txt
plover_keyboard_plus-0.0.5.dist-info/top_level.txt
plover_keyboard_plus-0.0.5.dist-info/zip-safe
plover_keyboard_plus-0.0.5.dist-info/RECORD
